{"status":0,"msg":{"gameInfo":{"region":"HN1","gameId":4555565471,"mapId":11,"gameMode":"CLASSIC","gameMutators":["Banana","Moments","NewSummonerBadgeSystem(1)","ModeProgression(1)","MSIWinner(6)","SRTrophyWinner(8)"],"gameType":"MATCHED_GAME","gameName":"teambuilder-match-4555565471","gameCreationTime":1576517915980,"gameTypeId":19,"queueId":430,"seasonId":0,"bannedChampions":[],"gameStartTimestamp":1576517919460,"gameVersion":"9.24.300.6382","gameServerName":""},"gameStats":{"completed":true,"finalFrameTimestamp":1576520155717,"teamStats":[{"teamId":100,"win":"Fail","firstBlood":false,"firstTower":false,"firstInhibitor":true,"firstBaron":false,"firstDragon":false,"firstRiftHerald":false,"towerKills":8,"inhibitorKills":2,"baronKills":0,"dragonKills":3,"vilemawKills":0,"riftHeraldKills":0},{"teamId":200,"win":"Win","firstBlood":true,"firstTower":true,"firstInhibitor":false,"firstBaron":true,"firstDragon":true,"firstRiftHerald":true,"towerKills":7,"inhibitorKills":1,"baronKills":1,"dragonKills":3,"vilemawKills":0,"riftHeraldKills":1}],"eventStats":[]},"participants":[{"originalAccountId":4134709545,"originalPlatformId":"HN1","currentAccountId":4134709545,"currentPlatformId":"HN1","teamId":100,"spell1Id":4,"spell2Id":11,"championId":64,"skinIndex":2,"profileIconId":4030,"summonerName":"\u6c61\u529b\u9017\u9017","teamParticipantId":1,"queueRating":1594,"stats":{"win":"Fail","winner":false,"leaver":false,"timePlayed":2199,"totalTimeSpentDisconnected":0,"champLevel":17,"item0":3071,"item1":3074,"item2":3036,"item3":1400,"item4":3147,"item5":3111,"item6":3340,"kills":18,"doubleKills":3,"tripleKills":0,"quadraKills":0,"pentaKills":0,"unrealKills":0,"largestKillingSpree":6,"largestMultiKill":2,"killingSprees":4,"longestTimeSpentLiving":541,"deaths":9,"totalTimeSpentDead":296,"assists":13,"totalDamageDealt":220946,"totalDamageTaken":53078,"largestCriticalStrike":0,"totalHeal":15443,"damageSelfMitigated":38692,"damageDealtToObjectives":14981,"damageDealtToTurrets":3560,"visionScore":21,"timeCCingOthers":31,"totalTimeCrowdControlDealt":329,"totalUnitsHealed":1,"minionsKilled":56,"neutralMinionsKilled":143,"neutralMinionsKilledTeamJungle":94,"neutralMinionsKilledEnemyJungle":30,"goldEarned":17014,"goldSpent":17010,"combatPlayerScore":0,"objectivePlayerScore":0,"playerScore0":0,"playerScore1":0,"playerScore2":0,"playerScore3":0,"playerScore4":0,"playerScore5":0,"playerScore6":0,"playerScore7":0,"playerScore8":0,"playerScore9":0,"playerScore10":0,"playerScore11":0,"totalPlayerScore":0,"totalScoreRank":0,"nodeCapture":0,"nodeCaptureAssist":0,"nodeNeutralize":0,"nodeNeutralizeAssist":0,"teamObjective":0,"magicDamageDealtToChampions":5470,"physicalDamageDealtToChampions":40227,"trueDamageDealtToChampions":2492,"totalDamageDealtToChampions":48189,"visionWardsBoughtInGame":5,"sightWardsBoughtInGame":0,"wardsPlaced":15,"wardsKilled":3,"magicDamageDealt":34413,"physicalDamageDealt":178740,"trueDamageDealt":7792,"magicDamageTaken":14794,"physicalDamageTaken":36589,"trueDamageTaken":1693,"firstBloodKill":false,"firstBloodAssist":false,"firstTowerKill":false,"firstTowerAssist":false,"firstInhibitorKill":false,"firstInhibitorAssist":false,"wasAfk":false,"wasAfkAfterFailedSurrender":false,"inhibitorKills":0,"towerKills":2,"gameEndedInEarlySurrender":false,"gameEndedInSurrender":false,"causedEarlySurrender":false,"earlySurrenderAccomplice":false,"teamEarlySurrendered":false,"championTransform":0,"spell1Casts":215,"spell2Casts":194,"spell3Casts":148,"spell4Casts":16,"summoner1Casts":5,"summoner2Casts":17,"perk0":8128,"perk0Var1":2367,"perk0Var2":25,"perk0Var3":514,"perk1":8143,"perk1Var1":1410,"perk1Var2":0,"perk1Var3":0,"perk2":8138,"perk2Var1":18,"perk2Var2":0,"perk2Var3":0,"perk3":8135,"perk3Var1":7710,"perk3Var2":5,"perk3Var3":0,"perk4":9111,"perk4Var1":2413,"perk4Var2":620,"perk4Var3":0,"perk5":8014,"perk5Var1":954,"perk5Var2":0,"perk5Var3":0,"perkPrimaryStyle":8100,"perkSubStyle":8000,"championMissionStat0":0,"championMissionStat1":0,"championMissionStat2":0,"championMissionStat3":0,"totalHealsOnTeammates":0,"totalDamageShieldedOnTeammates":1239,"teamPosition":"JUNGLE","individualPosition":"JUNGLE","statPerk0":5008,"statPerk1":5008,"statPerk2":5001},"timeAddedToQueue":1576517780247,"summonerId":4134709545,"wardSkin":121,"participantId":1,"partnerId":"","obfuscatedIP":"3VoTUXLOxMy1OmdTUitHpqfdYIc=","summonerLevel":104,"timeline":{"creepsPerMinDeltas":{"10-20":2.8,"0-10":0.2,"30-end":0.8,"20-30":2.1},"xpPerMinDeltas":{"10-20":671.1,"0-10":306.8,"30-end":176,"20-30":644.5},"goldPerMinDeltas":{"10-20":604.1,"0-10":302.9,"30-end":202.2,"20-30":512.5},"csDiffPerMinDeltas":{"10-20":1.2,"0-10":0.1,"30-end":-0.3999999999999999,"20-30":0.20000000000000007},"xpDiffPerMinDeltas":{"10-20":196.4,"0-10":0.9000000000000057,"30-end":-572,"20-30":222.7},"damageTakenPerMinDeltas":{"10-20":1403.6,"0-10":788.8,"30-end":1305.2,"20-30":2011.3999999999999},"damageTakenDiffPerMinDeltas":{"10-20":551.9,"0-10":-11.699999999999989,"30-end":-253,"20-30":317.0999999999999},"wardsPerMinDeltas":{"10-20":0.30000000000000004,"0-10":0.30000000000000004,"30-end":0.4,"20-30":0.6},"assistedLaneKillsPerMinDeltas":{"10-20":0,"0-10":0,"30-end":0,"20-30":0},"assistedLaneDeathsPerMinDeltas":{"10-20":0.1,"0-10":0.1,"30-end":0,"20-30":0.1},"towerKillsPerMinCounts":{"10-20":0,"0-10":0,"30-end":0,"20-30":0.2},"towerAssistsPerMinCounts":{"10-20":0,"0-10":0,"30-end":0,"20-30":0.1},"inhibitorKillsPerMinCounts":{"10-20":0,"0-10":0,"30-end":0,"20-30":0},"inhibitorAssistsPerMinCounts":{"10-20":0,"0-10":0,"30-end":0.2,"20-30":0},"baronKillsPerMinCounts":{"10-20":0,"0-10":0,"30-end":0,"20-30":0},"baronAssistsPerMinCounts":{"10-20":0,"0-10":0,"30-end":0,"20-30":0},"dragonKillsPerMinCounts":{"10-20":0.1,"0-10":0,"30-end":0,"20-30":0},"dragonAssistsPerMinCounts":{"10-20":0,"0-10":0,"30-end":0,"20-30":0},"vilemawKillsPerMinCounts":{"10-20":0,"0-10":0,"30-end":0,"20-30":0},"vilemawAssistsPerMinCounts":{"10-20":0,"0-10":0,"30-end":0,"20-30":0},"elderLizardKillsPerMinCounts":{"10-20":0.2,"0-10":0.1,"30-end":0,"20-30":0.1},"elderLizardAssistsPerMinCounts":{"10-20":0,"0-10":0,"30-end":0,"20-30":0},"ancientGolemKillsPerMinCounts":{"10-20":0.2,"0-10":0.1,"30-end":0,"20-30":0.1},"ancientGolemAssistsPerMinCounts":{"10-20":0,"0-10":0,"30-end":0,"20-30":0},"role":"NONE","lane":"JUNGLE"},"emoteIds":[3214,1487,0,1502,1492,1492,1492,1492,1492]},{"originalAccountId":4015111337,"originalPlatformId":"HN1","currentAccountId":4015111337,"currentPlatformId":"HN1","teamId":100,"spell1Id":4,"spell2Id":14,"championId":12,"skinIndex":10,"profileIconId":1385,"summonerName":"\u4f60\u7684\u5c0f\u5b9d\u8d1d\u5728\u8fd9\u5462","teamParticipantId":1,"queueRating":1395,"stats":{"win":"Fail","winner":false,"leaver":false,"timePlayed":2199,"totalTimeSpentDisconnected":0,"champLevel":16,"item0":3860,"item1":3800,"item2":3109,"item3":3117,"item4":3110,"item5":0,"item6":3364,"kills":8,"doubleKills":0,"tripleKills":0,"quadraKills":0,"pentaKills":0,"unrealKills":0,"largestKillingSpree":4,"largestMultiKill":1,"killingSprees":2,"longestTimeSpentLiving":562,"deaths":9,"totalTimeSpentDead":237,"assists":21,"totalDamageDealt":34400,"totalDamageTaken":34367,"largestCriticalStrike":0,"totalHeal":16380,"damageSelfMitigated":54841,"damageDealtToObjectives":493,"damageDealtToTurrets":493,"visionScore":31,"timeCCingOthers":65,"totalTimeCrowdControlDealt":529,"totalUnitsHealed":5,"minionsKilled":30,"neutralMinionsKilled":0,"neutralMinionsKilledTeamJungle":0,"neutralMinionsKilledEnemyJungle":0,"goldEarned":10579,"goldSpent":9100,"combatPlayerScore":0,"objectivePlayerScore":0,"playerScore0":0,"playerScore1":0,"playerScore2":0,"playerScore3":0,"playerScore4":0,"playerScore5":0,"playerScore6":0,"playerScore7":0,"playerScore8":0,"playerScore9":0,"playerScore10":0,"playerScore11":0,"totalPlayerScore":0,"totalScoreRank":0,"nodeCapture":0,"nodeCaptureAssist":0,"nodeNeutralize":0,"nodeNeutralizeAssist":0,"teamObjective":0,"magicDamageDealtToChampions":13516,"physicalDamageDealtToChampions":2447,"trueDamageDealtToChampions":1439,"totalDamageDealtToChampions":17402,"visionWardsBoughtInGame":2,"sightWardsBoughtInGame":0,"wardsPlaced":17,"wardsKilled":3,"magicDamageDealt":21312,"physicalDamageDealt":6143,"trueDamageDealt":6944,"magicDamageTaken":17260,"physicalDamageTaken":14045,"trueDamageTaken":3061,"firstBloodKill":false,"firstBloodAssist":false,"firstTowerKill":false,"firstTowerAssist":false,"firstInhibitorKill":false,"firstInhibitorAssist":false,"wasAfk":false,"wasAfkAfterFailedSurrender":false,"inhibitorKills":0,"towerKills":1,"gameEndedInEarlySurrender":false,"gameEndedInSurrender":false,"causedEarlySurrender":false,"earlySurrenderAccomplice":false,"teamEarlySurrendered":false,"championTransform":0,"spell1Casts":44,"spell2Casts":37,"spell3Casts":28,"spell4Casts":10,"summoner1Casts":4,"summoner2Casts":7,"perk0":8229,"perk0Var1":1281,"perk0Var2":0,"perk0Var3":0,"perk1":8224,"perk1Var1":1064,"perk1Var2":0,"perk1Var3":0,"perk2":8210,"perk2Var1":38,"perk2Var2":0,"perk2Var3":0,"perk3":8237,"perk3Var1":645,"perk3Var2":0,"perk3Var3":0,"perk4":8473,"perk4Var1":739,"perk4Var2":0,"perk4Var3":0,"perk5":8453,"perk5Var1":1577,"perk5Var2":334,"perk5Var3":0,"perkPrimaryStyle":8200,"perkSubStyle":8400,"championMissionStat0":0,"championMissionStat1":0,"championMissionStat2":0,"championMissionStat3":0,"totalHealsOnTeammates":7581,"totalDamageShieldedOnTeammates":0,"teamPosition":"UTILITY","individualPosition":"UTILITY","statPerk0":5007,"statPerk1":5008,"statPerk2":5002},"timeAddedToQueue":1576517780247,"summonerId":4015111337,"wardSkin":57,"participantId":2,"partnerId":"","obfuscatedIP":"3VoTUXLOxMy1OmdTUitHpqfdYIc=","summonerLevel":293,"timeline":{"creepsPerMinDeltas":{"10-20":0.8999999999999999,"0-10":1.3,"30-end":0.6,"20-30":0.5},"xpPerMinDeltas":{"10-20":499.6,"0-10":302.1,"30-end":201.4,"20-30":511.2},"goldPerMinDeltas":{"10-20":318,"0-10":207.60000000000002,"30-end":175.2,"20-30":371.5},"csDiffPerMinDeltas":{"10-20":1.7999999999999998,"0-10":-0.09999999999999964,"30-end":-1.1999999999999997,"20-30":-0.8},"xpDiffPerMinDeltas":{"10-20":257.25,"0-10":-4.099999999999966,"30-end":-541.3,"20-30":-20.09999999999991},"damageTakenPerMinDeltas":{"10-20":664.7,"0-10":405.8,"30-end":1495.6,"20-30":1329.1999999999998},"damageTakenDiffPerMinDeltas":{"10-20":105.19999999999999,"0-10":70.35000000000002,"30-end":379.29999999999995,"20-30":264.3499999999999},"wardsPerMinDeltas":{"10-20":0.5,"0-10":0.4,"30-end":0.4,"20-30":0.5},"assistedLaneKillsPerMinDeltas":{"10-20":0.1,"0-10":0,"30-end":0,"20-30":0.2},"assistedLaneDeathsPerMinDeltas":{"10-20":0,"0-10":0,"30-end":0.2,"20-30":0},"towerKillsPerMinCounts":{"10-20":0,"0-10":0,"30-end":0,"20-30":0.1},"towerAssistsPerMinCounts":{"10-20":0,"0-10":0,"30-end":0,"20-30":0.1},"inhibitorKillsPerMinCounts":{"10-20":0,"0-10":0,"30-end":0,"20-30":0},"inhibitorAssistsPerMinCounts":{"10-20":0,"0-10":0,"30-end":0.2,"20-30":0},"baronKillsPerMinCounts":{"10-20":0,"0-10":0,"30-end":0,"20-30":0},"baronAssistsPerMinCounts":{"10-20":0,"0-10":0,"30-end":0,"20-30":0},"dragonKillsPerMinCounts":{"10-20":0,"0-10":0,"30-end":0,"20-30":0},"dragonAssistsPerMinCounts":{"10-20":0,"0-10":0,"30-end":0,"20-30":0},"vilemawKillsPerMinCounts":{"10-20":0,"0-10":0,"30-end":0,"20-30":0},"vilemawAssistsPerMinCounts":{"10-20":0,"0-10":0,"30-end":0,"20-30":0},"elderLizardKillsPerMinCounts":{"10-20":0,"0-10":0,"30-end":0,"20-30":0},"elderLizardAssistsPerMinCounts":{"10-20":0,"0-10":0,"30-end":0,"20-30":0},"ancientGolemKillsPerMinCounts":{"10-20":0,"0-10":0,"30-end":0,"20-30":0},"ancientGolemAssistsPerMinCounts":{"10-20":0,"0-10":0,"30-end":0,"20-30":0},"role":"DUO_SUPPORT","lane":"BOTTOM"},"emoteIds":[1452,1469,3336,3335,3357,2033,3334,3148,1490]},{"originalAccountId":2941187201,"originalPlatformId":"HN1","currentAccountId":2941187201,"currentPlatformId":"HN1","teamId":100,"spell1Id":3,"spell2Id":4,"championId":157,"skinIndex":5,"profileIconId":3494,"summonerName":"\u6e23\u7537\u683c\u96f7\u798f\u65af","teamParticipantId":1,"queueRating":1712,"stats":{"win":"Fail","winner":false,"leaver":false,"timePlayed":2199,"totalTimeSpentDisconnected":1,"champLevel":18,"item0":3153,"item1":3031,"item2":3072,"item3":3078,"item4":3006,"item5":3095,"item6":3340,"kills":18,"doubleKills":3,"tripleKills":0,"quadraKills":0,"pentaKills":0,"unrealKills":0,"largestKillingSpree":8,"largestMultiKill":2,"killingSprees":4,"longestTimeSpentLiving":459,"deaths":11,"totalTimeSpentDead":363,"assists":14,"totalDamageDealt":251871,"totalDamageTaken":41240,"largestCriticalStrike":1033,"totalHeal":10053,"damageSelfMitigated":38141,"damageDealtToObjectives":11465,"damageDealtToTurrets":5425,"visionScore":16,"timeCCingOthers":48,"totalTimeCrowdControlDealt":224,"totalUnitsHealed":1,"minionsKilled":215,"neutralMinionsKilled":24,"neutralMinionsKilledTeamJungle":8,"neutralMinionsKilledEnemyJungle":12,"goldEarned":18949,"goldSpent":18933,"combatPlayerScore":0,"objectivePlayerScore":0,"playerScore0":0,"playerScore1":0,"playerScore2":0,"playerScore3":0,"playerScore4":0,"playerScore5":0,"playerScore6":0,"playerScore7":0,"playerScore8":0,"playerScore9":0,"playerScore10":0,"playerScore11":0,"totalPlayerScore":0,"totalScoreRank":0,"nodeCapture":0,"nodeCaptureAssist":0,"nodeNeutralize":0,"nodeNeutralizeAssist":0,"teamObjective":0,"magicDamageDealtToChampions":6184,"physicalDamageDealtToChampions":52000,"trueDamageDealtToChampions":1010,"totalDamageDealtToChampions":59196,"visionWardsBoughtInGame":0,"sightWardsBoughtInGame":0,"wardsPlaced":12,"wardsKilled":0,"magicDamageDealt":28116,"physicalDamageDealt":221234,"trueDamageDealt":2520,"magicDamageTaken":12840,"physicalDamageTaken":26127,"trueDamageTaken":2272,"firstBloodKill":false,"firstBloodAssist":false,"firstTowerKill":false,"firstTowerAssist":false,"firstInhibitorKill":false,"firstInhibitorAssist":true,"wasAfk":false,"wasAfkAfterFailedSurrender":false,"inhibitorKills":0,"towerKills":1,"gameEndedInEarlySurrender":false,"gameEndedInSurrender":false,"causedEarlySurrender":false,"earlySurrenderAccomplice":false,"teamEarlySurrendered":false,"championTransform":0,"spell1Casts":275,"spell2Casts":28,"spell3Casts":189,"spell4Casts":17,"summoner1Casts":8,"summoner2Casts":5,"perk0":8010,"perk0Var1":3835,"perk0Var2":0,"perk0Var3":0,"perk1":9111,"perk1Var1":1409,"perk1Var2":640,"perk1Var3":0,"perk2":9104,"perk2Var1":13,"perk2Var2":0,"perk2Var3":0,"perk3":8014,"perk3Var1":1522,"perk3Var2":0,"perk3Var3":0,"perk4":8139,"perk4Var1":1655,"perk4Var2":0,"perk4Var3":0,"perk5":8135,"perk5Var1":3235,"perk5Var2":5,"perk5Var3":0,"perkPrimaryStyle":8000,"perkSubStyle":8100,"championMissionStat0":0,"championMissionStat1":0,"championMissionStat2":0,"championMissionStat3":0,"totalHealsOnTeammates":0,"totalDamageShieldedOnTeammates":0,"teamPosition":"BOTTOM","individualPosition":"BOTTOM","statPerk0":5005,"statPerk1":5008,"statPerk2":5001},"timeAddedToQueue":1576517780247,"summonerId":2941187201,"wardSkin":111,"participantId":3,"partnerId":"","obfuscatedIP":"3VoTUXLOxMy1OmdTUitHpqfdYIc=","summonerLevel":297,"timeline":{"creepsPerMinDeltas":{"10-20":10,"0-10":4.9,"30-end":1.6,"20-30":5},"xpPerMinDeltas":{"10-20":631.2,"0-10":307.70000000000005,"30-end":424.6,"20-30":631.4000000000001},"goldPerMinDeltas":{"10-20":662.3,"0-10":321.2,"30-end":414.4,"20-30":602.4},"csDiffPerMinDeltas":{"10-20":1.7999999999999998,"0-10":-0.09999999999999964,"30-end":-1.1999999999999997,"20-30":-0.8},"xpDiffPerMinDeltas":{"10-20":257.25,"0-10":-4.099999999999966,"30-end":-541.3,"20-30":-20.09999999999991},"damageTakenPerMinDeltas":{"10-20":1062.4,"0-10":476.90000000000003,"30-end":1040.6,"20-30":1685.1},"damageTakenDiffPerMinDeltas":{"10-20":105.19999999999999,"0-10":70.35000000000002,"30-end":379.29999999999995,"20-30":264.3499999999999},"wardsPerMinDeltas":{"10-20":0.8,"0-10":0.4,"30-end":0.8,"20-30":1.2},"assistedLaneKillsPerMinDeltas":{"10-20":0,"0-10":0,"30-end":0,"20-30":0},"assistedLaneDeathsPerMinDeltas":{"10-20":0.2,"0-10":0.1,"30-end":0.2,"20-30":0},"towerKillsPerMinCounts":{"10-20":0,"0-10":0,"30-end":0,"20-30":0.1},"towerAssistsPerMinCounts":{"10-20":0,"0-10":0,"30-end":0,"20-30":0.2},"inhibitorKillsPerMinCounts":{"10-20":0,"0-10":0,"30-end":0,"20-30":0},"inhibitorAssistsPerMinCounts":{"10-20":0,"0-10":0,"30-end":0,"20-30":0.1},"baronKillsPerMinCounts":{"10-20":0,"0-10":0,"30-end":0,"20-30":0},"baronAssistsPerMinCounts":{"10-20":0,"0-10":0,"30-end":0,"20-30":0},"dragonKillsPerMinCounts":{"10-20":0,"0-10":0,"30-end":0,"20-30":0},"dragonAssistsPerMinCounts":{"10-20":0,"0-10":0,"30-end":0,"20-30":0},"vilemawKillsPerMinCounts":{"10-20":0,"0-10":0,"30-end":0,"20-30":0},"vilemawAssistsPerMinCounts":{"10-20":0,"0-10":0,"30-end":0,"20-30":0},"elderLizardKillsPerMinCounts":{"10-20":0,"0-10":0,"30-end":0.2,"20-30":0},"elderLizardAssistsPerMinCounts":{"10-20":0,"0-10":0,"30-end":0,"20-30":0},"ancientGolemKillsPerMinCounts":{"10-20":0,"0-10":0,"30-end":0,"20-30":0},"ancientGolemAssistsPerMinCounts":{"10-20":0,"0-10":0,"30-end":0,"20-30":0},"role":"DUO_CARRY","lane":"BOTTOM"},"emoteIds":[1499,1487,1030,1452,1492,1487,1030,3409,1499]},{"originalAccountId":4112764372,"originalPlatformId":"HN1","currentAccountId":4112764372,"currentPlatformId":"HN1","teamId":100,"spell1Id":4,"spell2Id":14,"championId":69,"skinIndex":2,"profileIconId":4218,"summonerName":"\u624b\u7529\u7280\u725b","teamParticipantId":2,"queueRating":1663,"stats":{"win":"Fail","winner":false,"leaver":false,"timePlayed":2199,"totalTimeSpentDisconnected":0,"champLevel":18,"item0":2421,"item1":3040,"item2":3165,"item3":1056,"item4":3116,"item5":3089,"item6":3363,"kills":6,"doubleKills":0,"tripleKills":0,"quadraKills":0,"pentaKills":0,"unrealKills":0,"largestKillingSpree":2,"largestMultiKill":1,"killingSprees":2,"longestTimeSpentLiving":686,"deaths":7,"totalTimeSpentDead":211,"assists":7,"totalDamageDealt":226483,"totalDamageTaken":32625,"largestCriticalStrike":0,"totalHeal":5215,"damageSelfMitigated":16901,"damageDealtToObjectives":13864,"damageDealtToTurrets":3879,"visionScore":30,"timeCCingOthers":25,"totalTimeCrowdControlDealt":671,"totalUnitsHealed":1,"minionsKilled":178,"neutralMinionsKilled":86,"neutralMinionsKilledTeamJungle":52,"neutralMinionsKilledEnemyJungle":16,"goldEarned":14679,"goldSpent":14050,"combatPlayerScore":0,"objectivePlayerScore":0,"playerScore0":0,"playerScore1":0,"playerScore2":0,"playerScore3":0,"playerScore4":0,"playerScore5":0,"playerScore6":0,"playerScore7":0,"playerScore8":0,"playerScore9":0,"playerScore10":0,"playerScore11":0,"totalPlayerScore":0,"totalScoreRank":0,"nodeCapture":0,"nodeCaptureAssist":0,"nodeNeutralize":0,"nodeNeutralizeAssist":0,"teamObjective":0,"magicDamageDealtToChampions":21196,"physicalDamageDealtToChampions":1249,"trueDamageDealtToChampions":1101,"totalDamageDealtToChampions":23547,"visionWardsBoughtInGame":1,"sightWardsBoughtInGame":0,"wardsPlaced":10,"wardsKilled":3,"magicDamageDealt":196966,"physicalDamageDealt":18476,"trueDamageDealt":11040,"magicDamageTaken":13102,"physicalDamageTaken":18675,"trueDamageTaken":847,"firstBloodKill":false,"firstBloodAssist":false,"firstTowerKill":false,"firstTowerAssist":false,"firstInhibitorKill":false,"firstInhibitorAssist":false,"wasAfk":false,"wasAfkAfterFailedSurrender":false,"inhibitorKills":0,"towerKills":1,"gameEndedInEarlySurrender":false,"gameEndedInSurrender":false,"causedEarlySurrender":false,"earlySurrenderAccomplice":false,"teamEarlySurrendered":false,"championTransform":0,"spell1Casts":220,"spell2Casts":34,"spell3Casts":497,"spell4Casts":11,"summoner1Casts":5,"summoner2Casts":5,"perk0":8010,"perk0Var1":815,"perk0Var2":0,"perk0Var3":0,"perk1":8009,"perk1Var1":3716,"perk1Var2":500,"perk1Var3":0,"perk2":9103,"perk2Var1":30,"perk2Var2":20,"perk2Var3":0,"perk3":8017,"perk3Var1":317,"perk3Var2":0,"perk3Var3":0,"perk4":8226,"perk4Var1":250,"perk4Var2":1727,"perk4Var3":0,"perk5":8210,"perk5Var1":0,"perk5Var2":0,"perk5Var3":0,"perkPrimaryStyle":8000,"perkSubStyle":8200,"championMissionStat0":0,"championMissionStat1":0,"championMissionStat2":0,"championMissionStat3":0,"totalHealsOnTeammates":0,"totalDamageShieldedOnTeammates":0,"teamPosition":"MIDDLE","individualPosition":"MIDDLE","statPerk0":5008,"statPerk1":5008,"statPerk2":5001},"timeAddedToQueue":1576517690565,"summonerId":4112764372,"wardSkin":56,"participantId":4,"partnerId":"","obfuscatedIP":"3VoTUXLOxMy1OmdTUitHpqfdYIc=","summonerLevel":232,"timeline":{"creepsPerMinDeltas":{"10-20":7.3,"0-10":6.4,"30-end":3.6,"20-30":1.6},"xpPerMinDeltas":{"10-20":583.5,"0-10":414.4,"30-end":758.4,"20-30":427.4},"goldPerMinDeltas":{"10-20":398.6,"0-10":247.6,"30-end":634.8,"20-30":381.6},"csDiffPerMinDeltas":{"10-20":1.4999999999999996,"0-10":-0.10000000000000009,"30-end":-1.6,"20-30":-2.2},"xpDiffPerMinDeltas":{"10-20":108.39999999999998,"0-10":-32.099999999999994,"30-end":-74.80000000000007,"20-30":-47.900000000000034},"damageTakenPerMinDeltas":{"10-20":475.70000000000005,"0-10":394.9,"30-end":2336,"20-30":882.6},"damageTakenDiffPerMinDeltas":{"10-20":-588.7,"0-10":-0.700000000000017,"30-end":633,"20-30":-864.5},"wardsPerMinDeltas":{"10-20":0.30000000000000004,"0-10":0.4,"30-end":0,"20-30":0.30000000000000004},"assistedLaneKillsPerMinDeltas":{"10-20":0.2,"0-10":0,"30-end":0,"20-30":0},"assistedLaneDeathsPerMinDeltas":{"10-20":0,"0-10":0,"30-end":0.2,"20-30":0},"towerKillsPerMinCounts":{"10-20":0,"0-10":0,"30-end":0,"20-30":0.1},"towerAssistsPerMinCounts":{"10-20":0,"0-10":0,"30-end":0,"20-30":0},"inhibitorKillsPerMinCounts":{"10-20":0,"0-10":0,"30-end":0,"20-30":0},"inhibitorAssistsPerMinCounts":{"10-20":0,"0-10":0,"30-end":0,"20-30":0},"baronKillsPerMinCounts":{"10-20":0,"0-10":0,"30-end":0,"20-30":0},"baronAssistsPerMinCounts":{"10-20":0,"0-10":0,"30-end":0,"20-30":0},"dragonKillsPerMinCounts":{"10-20":0,"0-10":0,"30-end":0.2,"20-30":0},"dragonAssistsPerMinCounts":{"10-20":0,"0-10":0,"30-end":0,"20-30":0},"vilemawKillsPerMinCounts":{"10-20":0,"0-10":0,"30-end":0,"20-30":0},"vilemawAssistsPerMinCounts":{"10-20":0,"0-10":0,"30-end":0,"20-30":0},"elderLizardKillsPerMinCounts":{"10-20":0,"0-10":0,"30-end":0.2,"20-30":0.2},"elderLizardAssistsPerMinCounts":{"10-20":0,"0-10":0,"30-end":0,"20-30":0},"ancientGolemKillsPerMinCounts":{"10-20":0,"0-10":0,"30-end":0.4,"20-30":0.2},"ancientGolemAssistsPerMinCounts":{"10-20":0,"0-10":0,"30-end":0,"20-30":0},"role":"SOLO","lane":"MID"},"emoteIds":[1469,998,3242,3135,1459,1452,1444,1030,1030]},{"originalAccountId":2941638261,"originalPlatformId":"HN1","currentAccountId":2941638261,"currentPlatformId":"HN1","teamId":100,"spell1Id":12,"spell2Id":4,"championId":84,"skinIndex":7,"profileIconId":3494,"summonerName":"\u5c0f\u751f\u4e36\u672a\u767d","teamParticipantId":2,"queueRating":1494,"stats":{"win":"Fail","winner":false,"leaver":false,"timePlayed":2199,"totalTimeSpentDisconnected":0,"champLevel":17,"item0":3146,"item1":3165,"item2":3135,"item3":1082,"item4":0,"item5":3020,"item6":3364,"kills":4,"doubleKills":0,"tripleKills":0,"quadraKills":0,"pentaKills":0,"unrealKills":0,"largestKillingSpree":3,"largestMultiKill":1,"killingSprees":1,"longestTimeSpentLiving":592,"deaths":9,"totalTimeSpentDead":294,"assists":7,"totalDamageDealt":131263,"totalDamageTaken":32048,"largestCriticalStrike":0,"totalHeal":6329,"damageSelfMitigated":20895,"damageDealtToObjectives":5546,"damageDealtToTurrets":5546,"visionScore":26,"timeCCingOthers":6,"totalTimeCrowdControlDealt":97,"totalUnitsHealed":1,"minionsKilled":179,"neutralMinionsKilled":4,"neutralMinionsKilledTeamJungle":4,"neutralMinionsKilledEnemyJungle":0,"goldEarned":11326,"goldSpent":11275,"combatPlayerScore":0,"objectivePlayerScore":0,"playerScore0":0,"playerScore1":0,"playerScore2":0,"playerScore3":0,"playerScore4":0,"playerScore5":0,"playerScore6":0,"playerScore7":0,"playerScore8":0,"playerScore9":0,"playerScore10":0,"playerScore11":0,"totalPlayerScore":0,"totalScoreRank":0,"nodeCapture":0,"nodeCaptureAssist":0,"nodeNeutralize":0,"nodeNeutralizeAssist":0,"teamObjective":0,"magicDamageDealtToChampions":11474,"physicalDamageDealtToChampions":4864,"trueDamageDealtToChampions":341,"totalDamageDealtToChampions":16679,"visionWardsBoughtInGame":7,"sightWardsBoughtInGame":0,"wardsPlaced":11,"wardsKilled":1,"magicDamageDealt":98356,"physicalDamageDealt":32565,"trueDamageDealt":341,"magicDamageTaken":6984,"physicalDamageTaken":24357,"trueDamageTaken":706,"firstBloodKill":false,"firstBloodAssist":false,"firstTowerKill":false,"firstTowerAssist":false,"firstInhibitorKill":false,"firstInhibitorAssist":false,"wasAfk":false,"wasAfkAfterFailedSurrender":false,"inhibitorKills":1,"towerKills":2,"gameEndedInEarlySurrender":false,"gameEndedInSurrender":false,"causedEarlySurrender":false,"earlySurrenderAccomplice":false,"teamEarlySurrendered":false,"championTransform":0,"spell1Casts":145,"spell2Casts":22,"spell3Casts":71,"spell4Casts":15,"summoner1Casts":4,"summoner2Casts":5,"perk0":8021,"perk0Var1":3186,"perk0Var2":0,"perk0Var3":0,"perk1":9101,"perk1Var1":3732,"perk1Var2":3971,"perk1Var3":0,"perk2":9105,"perk2Var1":20,"perk2Var2":40,"perk2Var3":0,"perk3":8299,"perk3Var1":449,"perk3Var2":0,"perk3Var3":0,"perk4":8304,"perk4Var1":10,"perk4Var2":3,"perk4Var3":0,"perk5":8345,"perk5Var1":3,"perk5Var2":0,"perk5Var3":0,"perkPrimaryStyle":8000,"perkSubStyle":8300,"championMissionStat0":0,"championMissionStat1":0,"championMissionStat2":0,"championMissionStat3":0,"totalHealsOnTeammates":0,"totalDamageShieldedOnTeammates":0,"teamPosition":"TOP","individualPosition":"TOP","statPerk0":5008,"statPerk1":5008,"statPerk2":5001},"timeAddedToQueue":1576517690565,"summonerId":2941638261,"wardSkin":132,"participantId":5,"partnerId":"","obfuscatedIP":"3VoTUXLOxMy1OmdTUitHpqfdYIc=","summonerLevel":181,"timeline":{"creepsPerMinDeltas":{"10-20":6.3,"0-10":4.5,"30-end":4.4,"20-30":4.5},"xpPerMinDeltas":{"10-20":470.5,"0-10":423.7,"30-end":308.6,"20-30":506.1},"goldPerMinDeltas":{"10-20":324,"0-10":233.2,"30-end":247.2,"20-30":359.29999999999995},"csDiffPerMinDeltas":{"10-20":-1,"0-10":-1.9,"30-end":2.4000000000000004,"20-30":-0.8999999999999999},"xpDiffPerMinDeltas":{"10-20":-150,"0-10":-33.19999999999999,"30-end":-453.6,"20-30":23.80000000000001},"damageTakenPerMinDeltas":{"10-20":749.8,"0-10":548.2,"30-end":986.6,"20-30":1060.5},"damageTakenDiffPerMinDeltas":{"10-20":-463.99999999999994,"0-10":23.099999999999994,"30-end":-1070.4,"20-30":-1211.6000000000001},"wardsPerMinDeltas":{"10-20":0.4,"0-10":0.4,"30-end":0.2,"20-30":0.2},"assistedLaneKillsPerMinDeltas":{"10-20":0,"0-10":0,"30-end":0,"20-30":0.1},"assistedLaneDeathsPerMinDeltas":{"10-20":0,"0-10":0.1,"30-end":0,"20-30":0},"towerKillsPerMinCounts":{"10-20":0,"0-10":0,"30-end":0.2,"20-30":0},"towerAssistsPerMinCounts":{"10-20":0,"0-10":0,"30-end":0,"20-30":0.1},"inhibitorKillsPerMinCounts":{"10-20":0,"0-10":0,"30-end":0.2,"20-30":0},"inhibitorAssistsPerMinCounts":{"10-20":0,"0-10":0,"30-end":0,"20-30":0},"baronKillsPerMinCounts":{"10-20":0,"0-10":0,"30-end":0,"20-30":0},"baronAssistsPerMinCounts":{"10-20":0,"0-10":0,"30-end":0,"20-30":0},"dragonKillsPerMinCounts":{"10-20":0,"0-10":0,"30-end":0,"20-30":0},"dragonAssistsPerMinCounts":{"10-20":0,"0-10":0,"30-end":0,"20-30":0},"vilemawKillsPerMinCounts":{"10-20":0,"0-10":0,"30-end":0,"20-30":0},"vilemawAssistsPerMinCounts":{"10-20":0,"0-10":0,"30-end":0,"20-30":0},"elderLizardKillsPerMinCounts":{"10-20":0,"0-10":0,"30-end":0,"20-30":0},"elderLizardAssistsPerMinCounts":{"10-20":0,"0-10":0,"30-end":0,"20-30":0},"ancientGolemKillsPerMinCounts":{"10-20":0,"0-10":0,"30-end":0,"20-30":0},"ancientGolemAssistsPerMinCounts":{"10-20":0,"0-10":0,"30-end":0,"20-30":0},"role":"SOLO","lane":"TOP"},"emoteIds":[1474,1489,1468,1462,1459,1459,3343,1474,1474]},{"originalAccountId":4119555065,"originalPlatformId":"HN1","currentAccountId":4119555065,"currentPlatformId":"HN1","teamId":200,"spell1Id":4,"spell2Id":11,"championId":11,"skinIndex":0,"profileIconId":4430,"summonerName":"\u7cd7\u53cb\u6cdb","teamParticipantId":3,"queueRating":1567,"stats":{"win":"Win","winner":true,"leaver":false,"timePlayed":2199,"totalTimeSpentDisconnected":0,"champLevel":17,"item0":3143,"item1":1419,"item2":3006,"item3":3181,"item4":3124,"item5":3067,"item6":3340,"kills":11,"doubleKills":1,"tripleKills":0,"quadraKills":0,"pentaKills":0,"unrealKills":0,"largestKillingSpree":3,"largestMultiKill":2,"killingSprees":4,"longestTimeSpentLiving":619,"deaths":11,"totalTimeSpentDead":394,"assists":14,"totalDamageDealt":189922,"totalDamageTaken":43547,"largestCriticalStrike":0,"totalHeal":14619,"damageSelfMitigated":34191,"damageDealtToObjectives":31291,"damageDealtToTurrets":1291,"visionScore":35,"timeCCingOthers":5,"totalTimeCrowdControlDealt":197,"totalUnitsHealed":1,"minionsKilled":48,"neutralMinionsKilled":111,"neutralMinionsKilledTeamJungle":71,"neutralMinionsKilledEnemyJungle":4,"goldEarned":15140,"goldSpent":13775,"combatPlayerScore":0,"objectivePlayerScore":0,"playerScore0":0,"playerScore1":0,"playerScore2":0,"playerScore3":0,"playerScore4":0,"playerScore5":0,"playerScore6":0,"playerScore7":0,"playerScore8":0,"playerScore9":0,"playerScore10":0,"playerScore11":0,"totalPlayerScore":0,"totalScoreRank":0,"nodeCapture":0,"nodeCaptureAssist":0,"nodeNeutralize":0,"nodeNeutralizeAssist":0,"teamObjective":0,"magicDamageDealtToChampions":366,"physicalDamageDealtToChampions":23517,"trueDamageDealtToChampions":5883,"totalDamageDealtToChampions":29767,"visionWardsBoughtInGame":0,"sightWardsBoughtInGame":0,"wardsPlaced":13,"wardsKilled":6,"magicDamageDealt":5653,"physicalDamageDealt":151206,"trueDamageDealt":33060,"magicDamageTaken":11347,"physicalDamageTaken":31060,"trueDamageTaken":1139,"firstBloodKill":true,"firstBloodAssist":false,"firstTowerKill":false,"firstTowerAssist":false,"firstInhibitorKill":false,"firstInhibitorAssist":false,"wasAfk":false,"wasAfkAfterFailedSurrender":false,"inhibitorKills":0,"towerKills":1,"gameEndedInEarlySurrender":false,"gameEndedInSurrender":false,"causedEarlySurrender":false,"earlySurrenderAccomplice":false,"teamEarlySurrendered":false,"championTransform":0,"spell1Casts":90,"spell2Casts":13,"spell3Casts":44,"spell4Casts":14,"summoner1Casts":5,"summoner2Casts":21,"perk0":8010,"perk0Var1":1417,"perk0Var2":0,"perk0Var3":0,"perk1":9111,"perk1Var1":1727,"perk1Var2":500,"perk1Var3":0,"perk2":9104,"perk2Var1":9,"perk2Var2":40,"perk2Var3":0,"perk3":8014,"perk3Var1":767,"perk3Var2":0,"perk3Var3":0,"perk4":8135,"perk4Var1":6790,"perk4Var2":5,"perk4Var3":0,"perk5":8143,"perk5Var1":764,"perk5Var2":0,"perk5Var3":0,"perkPrimaryStyle":8000,"perkSubStyle":8100,"championMissionStat0":0,"championMissionStat1":0,"championMissionStat2":0,"championMissionStat3":0,"totalHealsOnTeammates":0,"totalDamageShieldedOnTeammates":0,"teamPosition":"JUNGLE","individualPosition":"JUNGLE","statPerk0":5005,"statPerk1":5008,"statPerk2":5002},"timeAddedToQueue":1576517687020,"summonerId":4119555065,"wardSkin":49,"participantId":6,"partnerId":"","obfuscatedIP":"3VoTUXLOxMy1OmdTUitHpqfdYIc=","summonerLevel":271,"timeline":{"creepsPerMinDeltas":{"10-20":1.6,"0-10":0.1,"30-end":1.2,"20-30":1.9},"xpPerMinDeltas":{"10-20":474.70000000000005,"0-10":305.9,"30-end":748,"20-30":421.8},"goldPerMinDeltas":{"10-20":397.29999999999995,"0-10":355.7,"30-end":406,"20-30":376},"csDiffPerMinDeltas":{"10-20":-1.2,"0-10":-0.1,"30-end":0.3999999999999999,"20-30":-0.20000000000000007},"xpDiffPerMinDeltas":{"10-20":-196.4,"0-10":-0.9000000000000057,"30-end":572,"20-30":-222.7},"damageTakenPerMinDeltas":{"10-20":851.7,"0-10":800.5,"30-end":1558.2,"20-30":1694.3},"damageTakenDiffPerMinDeltas":{"10-20":-551.9,"0-10":11.699999999999989,"30-end":253,"20-30":-317.0999999999999},"wardsPerMinDeltas":{"10-20":0.30000000000000004,"0-10":0.30000000000000004,"30-end":0.4,"20-30":0.4},"assistedLaneKillsPerMinDeltas":{"10-20":0.1,"0-10":0.1,"30-end":0,"20-30":0.1},"assistedLaneDeathsPerMinDeltas":{"10-20":0,"0-10":0,"30-end":0,"20-30":0},"towerKillsPerMinCounts":{"10-20":0,"0-10":0,"30-end":0,"20-30":0},"towerAssistsPerMinCounts":{"10-20":0,"0-10":0,"30-end":0,"20-30":0},"inhibitorKillsPerMinCounts":{"10-20":0,"0-10":0,"30-end":0,"20-30":0},"inhibitorAssistsPerMinCounts":{"10-20":0,"0-10":0,"30-end":0,"20-30":0},"baronKillsPerMinCounts":{"10-20":0,"0-10":0,"30-end":0,"20-30":0},"baronAssistsPerMinCounts":{"10-20":0,"0-10":0,"30-end":0,"20-30":0},"dragonKillsPerMinCounts":{"10-20":0.1,"0-10":0,"30-end":0,"20-30":0.2},"dragonAssistsPerMinCounts":{"10-20":0,"0-10":0,"30-end":0,"20-30":0},"vilemawKillsPerMinCounts":{"10-20":0,"0-10":0,"30-end":0,"20-30":0},"vilemawAssistsPerMinCounts":{"10-20":0,"0-10":0,"30-end":0,"20-30":0},"elderLizardKillsPerMinCounts":{"10-20":0.1,"0-10":0.1,"30-end":0,"20-30":0.1},"elderLizardAssistsPerMinCounts":{"10-20":0,"0-10":0,"30-end":0,"20-30":0},"ancientGolemKillsPerMinCounts":{"10-20":0,"0-10":0.1,"30-end":0,"20-30":0},"ancientGolemAssistsPerMinCounts":{"10-20":0,"0-10":0,"30-end":0,"20-30":0},"role":"NONE","lane":"JUNGLE"},"emoteIds":[1498,3278,3115,3408,1492,3115,3278,997,1492]},{"originalAccountId":2969221358,"originalPlatformId":"HN1","currentAccountId":2969221358,"currentPlatformId":"HN1","teamId":200,"spell1Id":3,"spell2Id":4,"championId":26,"skinIndex":5,"profileIconId":4379,"summonerName":"\u8046\u542c\u90a3\u4f24\u611f","teamParticipantId":4,"queueRating":1564,"stats":{"win":"Win","winner":true,"leaver":false,"timePlayed":2199,"totalTimeSpentDisconnected":0,"champLevel":16,"item0":3853,"item1":3157,"item2":3105,"item3":3020,"item4":1082,"item5":3165,"item6":3364,"kills":0,"doubleKills":0,"tripleKills":0,"quadraKills":0,"pentaKills":0,"unrealKills":0,"largestKillingSpree":0,"largestMultiKill":0,"killingSprees":0,"longestTimeSpentLiving":528,"deaths":10,"totalTimeSpentDead":313,"assists":26,"totalDamageDealt":60769,"totalDamageTaken":29927,"largestCriticalStrike":0,"totalHeal":10021,"damageSelfMitigated":19812,"damageDealtToObjectives":3605,"damageDealtToTurrets":2787,"visionScore":87,"timeCCingOthers":24,"totalTimeCrowdControlDealt":218,"totalUnitsHealed":3,"minionsKilled":59,"neutralMinionsKilled":4,"neutralMinionsKilledTeamJungle":0,"neutralMinionsKilledEnemyJungle":0,"goldEarned":9901,"goldSpent":9425,"combatPlayerScore":0,"objectivePlayerScore":0,"playerScore0":0,"playerScore1":0,"playerScore2":0,"playerScore3":0,"playerScore4":0,"playerScore5":0,"playerScore6":0,"playerScore7":0,"playerScore8":0,"playerScore9":0,"playerScore10":0,"playerScore11":0,"totalPlayerScore":0,"totalScoreRank":0,"nodeCapture":0,"nodeCaptureAssist":0,"nodeNeutralize":0,"nodeNeutralizeAssist":0,"teamObjective":0,"magicDamageDealtToChampions":10514,"physicalDamageDealtToChampions":1391,"trueDamageDealtToChampions":5,"totalDamageDealtToChampions":11910,"visionWardsBoughtInGame":5,"sightWardsBoughtInGame":0,"wardsPlaced":41,"wardsKilled":3,"magicDamageDealt":57021,"physicalDamageDealt":3743,"trueDamageDealt":5,"magicDamageTaken":8917,"physicalDamageTaken":20426,"trueDamageTaken":584,"firstBloodKill":false,"firstBloodAssist":false,"firstTowerKill":false,"firstTowerAssist":false,"firstInhibitorKill":false,"firstInhibitorAssist":false,"wasAfk":false,"wasAfkAfterFailedSurrender":false,"inhibitorKills":0,"towerKills":2,"gameEndedInEarlySurrender":false,"gameEndedInSurrender":false,"causedEarlySurrender":false,"earlySurrenderAccomplice":false,"teamEarlySurrendered":false,"championTransform":0,"spell1Casts":226,"spell2Casts":102,"spell3Casts":97,"spell4Casts":11,"summoner1Casts":8,"summoner2Casts":5,"perk0":8214,"perk0Var1":1526,"perk0Var2":1797,"perk0Var3":0,"perk1":8226,"perk1Var1":250,"perk1Var2":1206,"perk1Var3":0,"perk2":8210,"perk2Var1":0,"perk2Var2":0,"perk2Var3":0,"perk3":8236,"perk3Var1":48,"perk3Var2":0,"perk3Var3":0,"perk4":8345,"perk4Var1":3,"perk4Var2":0,"perk4Var3":0,"perk5":8352,"perk5Var1":70,"perk5Var2":362,"perk5Var3":52,"perkPrimaryStyle":8200,"perkSubStyle":8300,"championMissionStat0":0,"championMissionStat1":0,"championMissionStat2":0,"championMissionStat3":0,"totalHealsOnTeammates":3978,"totalDamageShieldedOnTeammates":1894,"teamPosition":"UTILITY","individualPosition":"UTILITY","statPerk0":5007,"statPerk1":5008,"statPerk2":5001},"timeAddedToQueue":1576517668221,"summonerId":2969221358,"wardSkin":77,"participantId":7,"partnerId":"","obfuscatedIP":"3VoTUXLOxMy1OmdTUitHpqfdYIc=","summonerLevel":388,"timeline":{"creepsPerMinDeltas":{"10-20":1.4,"0-10":1,"30-end":1.2,"20-30":2.9},"xpPerMinDeltas":{"10-20":250.3,"0-10":301.79999999999995,"30-end":895.4,"20-30":609.3},"goldPerMinDeltas":{"10-20":240.4,"0-10":221,"30-end":418.2,"20-30":246.5},"csDiffPerMinDeltas":{"10-20":-1.7999999999999998,"0-10":0.09999999999999964,"30-end":1.1999999999999997,"20-30":0.8},"xpDiffPerMinDeltas":{"10-20":-257.25,"0-10":4.099999999999966,"30-end":541.3,"20-30":20.09999999999991},"damageTakenPerMinDeltas":{"10-20":984.5999999999999,"0-10":312.5,"30-end":648,"20-30":1139.4},"damageTakenDiffPerMinDeltas":{"10-20":-105.19999999999999,"0-10":-70.35000000000002,"30-end":-379.29999999999995,"20-30":-264.3499999999999},"wardsPerMinDeltas":{"10-20":1,"0-10":0.7,"30-end":2.2,"20-30":1.2999999999999998},"assistedLaneKillsPerMinDeltas":{"10-20":0,"0-10":0,"30-end":0,"20-30":0},"assistedLaneDeathsPerMinDeltas":{"10-20":0.1,"0-10":0,"30-end":0,"20-30":0.1},"towerKillsPerMinCounts":{"10-20":0,"0-10":0,"30-end":0,"20-30":0},"towerAssistsPerMinCounts":{"10-20":0,"0-10":0,"30-end":0,"20-30":0},"inhibitorKillsPerMinCounts":{"10-20":0,"0-10":0,"30-end":0,"20-30":0},"inhibitorAssistsPerMinCounts":{"10-20":0,"0-10":0,"30-end":0,"20-30":0},"baronKillsPerMinCounts":{"10-20":0,"0-10":0,"30-end":0,"20-30":0},"baronAssistsPerMinCounts":{"10-20":0,"0-10":0,"30-end":0,"20-30":0},"dragonKillsPerMinCounts":{"10-20":0,"0-10":0,"30-end":0,"20-30":0},"dragonAssistsPerMinCounts":{"10-20":0,"0-10":0,"30-end":0,"20-30":0},"vilemawKillsPerMinCounts":{"10-20":0,"0-10":0,"30-end":0,"20-30":0},"vilemawAssistsPerMinCounts":{"10-20":0,"0-10":0,"30-end":0,"20-30":0},"elderLizardKillsPerMinCounts":{"10-20":0,"0-10":0,"30-end":0,"20-30":0},"elderLizardAssistsPerMinCounts":{"10-20":0,"0-10":0,"30-end":0,"20-30":0},"ancientGolemKillsPerMinCounts":{"10-20":0,"0-10":0,"30-end":0,"20-30":0},"ancientGolemAssistsPerMinCounts":{"10-20":0,"0-10":0,"30-end":0,"20-30":0},"role":"DUO_SUPPORT","lane":"BOTTOM"},"emoteIds":[3104,3000,3114,3001,1459,1478,1462,3148,3123]},{"originalAccountId":4106165477,"originalPlatformId":"HN1","currentAccountId":4106165477,"currentPlatformId":"HN1","teamId":200,"spell1Id":7,"spell2Id":4,"championId":81,"skinIndex":8,"profileIconId":4409,"summonerName":"\u706c\u6b4c\u5c3d\u6843\u82b1\u6247\u5e95\u98ce","teamParticipantId":5,"queueRating":1636,"stats":{"win":"Win","winner":true,"leaver":false,"timePlayed":2199,"totalTimeSpentDisconnected":0,"champLevel":17,"item0":3153,"item1":3042,"item2":3111,"item3":3078,"item4":3095,"item5":1055,"item6":3340,"kills":12,"doubleKills":1,"tripleKills":0,"quadraKills":0,"pentaKills":0,"unrealKills":0,"largestKillingSpree":4,"largestMultiKill":2,"killingSprees":2,"longestTimeSpentLiving":292,"deaths":11,"totalTimeSpentDead":339,"assists":15,"totalDamageDealt":176585,"totalDamageTaken":31252,"largestCriticalStrike":0,"totalHeal":2444,"damageSelfMitigated":16177,"damageDealtToObjectives":14058,"damageDealtToTurrets":4818,"visionScore":23,"timeCCingOthers":7,"totalTimeCrowdControlDealt":63,"totalUnitsHealed":4,"minionsKilled":175,"neutralMinionsKilled":15,"neutralMinionsKilledTeamJungle":12,"neutralMinionsKilledEnemyJungle":0,"goldEarned":14977,"goldSpent":13933,"combatPlayerScore":0,"objectivePlayerScore":0,"playerScore0":0,"playerScore1":0,"playerScore2":0,"playerScore3":0,"playerScore4":0,"playerScore5":0,"playerScore6":0,"playerScore7":0,"playerScore8":0,"playerScore9":0,"playerScore10":0,"playerScore11":0,"totalPlayerScore":0,"totalScoreRank":0,"nodeCapture":0,"nodeCaptureAssist":0,"nodeNeutralize":0,"nodeNeutralizeAssist":0,"teamObjective":0,"magicDamageDealtToChampions":14043,"physicalDamageDealtToChampions":31127,"trueDamageDealtToChampions":1221,"totalDamageDealtToChampions":46391,"visionWardsBoughtInGame":0,"sightWardsBoughtInGame":0,"wardsPlaced":13,"wardsKilled":4,"magicDamageDealt":22925,"physicalDamageDealt":146625,"trueDamageDealt":7034,"magicDamageTaken":10728,"physicalDamageTaken":19956,"trueDamageTaken":568,"firstBloodKill":false,"firstBloodAssist":false,"firstTowerKill":false,"firstTowerAssist":false,"firstInhibitorKill":false,"firstInhibitorAssist":false,"wasAfk":false,"wasAfkAfterFailedSurrender":false,"inhibitorKills":0,"towerKills":2,"gameEndedInEarlySurrender":false,"gameEndedInSurrender":false,"causedEarlySurrender":false,"earlySurrenderAccomplice":false,"teamEarlySurrendered":false,"championTransform":0,"spell1Casts":345,"spell2Casts":63,"spell3Casts":54,"spell4Casts":17,"summoner1Casts":7,"summoner2Casts":5,"perk0":8358,"perk0Var1":34,"perk0Var2":1000,"perk0Var3":24,"perk1":8304,"perk1Var1":8,"perk1Var2":1,"perk1Var3":5,"perk2":8345,"perk2Var1":3,"perk2Var2":0,"perk2Var3":0,"perk3":8347,"perk3Var1":0,"perk3Var2":0,"perk3Var3":0,"perk4":8226,"perk4Var1":250,"perk4Var2":1935,"perk4Var3":0,"perk5":8210,"perk5Var1":0,"perk5Var2":0,"perk5Var3":0,"perkPrimaryStyle":8300,"perkSubStyle":8200,"championMissionStat0":0,"championMissionStat1":0,"championMissionStat2":0,"championMissionStat3":0,"totalHealsOnTeammates":622,"totalDamageShieldedOnTeammates":0,"teamPosition":"BOTTOM","individualPosition":"BOTTOM","statPerk0":5005,"statPerk1":5008,"statPerk2":5002},"timeAddedToQueue":1576517784291,"summonerId":4106165477,"wardSkin":52,"participantId":8,"partnerId":"","obfuscatedIP":"3VoTUXLOxMy1OmdTUitHpqfdYIc=","summonerLevel":275,"timeline":{"creepsPerMinDeltas":{"10-20":5.9,"0-10":5.4,"30-end":3.4,"20-30":4.2},"xpPerMinDeltas":{"10-20":366,"0-10":316.2,"30-end":813.2,"20-30":573.5},"goldPerMinDeltas":{"10-20":364.20000000000005,"0-10":390.5,"30-end":644.6,"20-30":326.8},"csDiffPerMinDeltas":{"10-20":-1.7999999999999998,"0-10":0.09999999999999964,"30-end":1.1999999999999997,"20-30":0.8},"xpDiffPerMinDeltas":{"10-20":-257.25,"0-10":4.099999999999966,"30-end":541.3,"20-30":20.09999999999991},"damageTakenPerMinDeltas":{"10-20":532.0999999999999,"0-10":429.5,"30-end":1129.6,"20-30":1346.2},"damageTakenDiffPerMinDeltas":{"10-20":-105.19999999999999,"0-10":-70.35000000000002,"30-end":-379.29999999999995,"20-30":-264.3499999999999},"wardsPerMinDeltas":{"10-20":0.4,"0-10":0.2,"30-end":0.4,"20-30":0.4},"assistedLaneKillsPerMinDeltas":{"10-20":0.2,"0-10":0.1,"30-end":0.4,"20-30":0},"assistedLaneDeathsPerMinDeltas":{"10-20":0,"0-10":0,"30-end":0,"20-30":0.1},"towerKillsPerMinCounts":{"10-20":0.1,"0-10":0,"30-end":0,"20-30":0},"towerAssistsPerMinCounts":{"10-20":0,"0-10":0,"30-end":0,"20-30":0},"inhibitorKillsPerMinCounts":{"10-20":0,"0-10":0,"30-end":0,"20-30":0},"inhibitorAssistsPerMinCounts":{"10-20":0,"0-10":0,"30-end":0,"20-30":0},"baronKillsPerMinCounts":{"10-20":0,"0-10":0,"30-end":0,"20-30":0},"baronAssistsPerMinCounts":{"10-20":0,"0-10":0,"30-end":0,"20-30":0},"dragonKillsPerMinCounts":{"10-20":0,"0-10":0,"30-end":0,"20-30":0},"dragonAssistsPerMinCounts":{"10-20":0,"0-10":0,"30-end":0,"20-30":0},"vilemawKillsPerMinCounts":{"10-20":0,"0-10":0,"30-end":0,"20-30":0},"vilemawAssistsPerMinCounts":{"10-20":0,"0-10":0,"30-end":0,"20-30":0},"elderLizardKillsPerMinCounts":{"10-20":0,"0-10":0,"30-end":0,"20-30":0},"elderLizardAssistsPerMinCounts":{"10-20":0,"0-10":0,"30-end":0,"20-30":0},"ancientGolemKillsPerMinCounts":{"10-20":0,"0-10":0,"30-end":0,"20-30":0},"ancientGolemAssistsPerMinCounts":{"10-20":0,"0-10":0,"30-end":0,"20-30":0},"role":"DUO_CARRY","lane":"BOTTOM"},"emoteIds":[3351,1473,3357,1487,3279,3351,3279,1473,3351]},{"originalAccountId":2978868743,"originalPlatformId":"HN1","currentAccountId":2978868743,"currentPlatformId":"HN1","teamId":200,"spell1Id":12,"spell2Id":4,"championId":266,"skinIndex":2,"profileIconId":4057,"summonerName":"Cancerlh","teamParticipantId":5,"queueRating":1478,"stats":{"win":"Win","winner":true,"leaver":false,"timePlayed":2199,"totalTimeSpentDisconnected":0,"champLevel":18,"item0":3812,"item1":3053,"item2":3142,"item3":3071,"item4":3047,"item5":0,"item6":3364,"kills":7,"doubleKills":0,"tripleKills":0,"quadraKills":0,"pentaKills":0,"unrealKills":0,"largestKillingSpree":3,"largestMultiKill":1,"killingSprees":2,"longestTimeSpentLiving":519,"deaths":10,"totalTimeSpentDead":419,"assists":14,"totalDamageDealt":177321,"totalDamageTaken":52914,"largestCriticalStrike":0,"totalHeal":18971,"damageSelfMitigated":50024,"damageDealtToObjectives":9245,"damageDealtToTurrets":4408,"visionScore":10,"timeCCingOthers":19,"totalTimeCrowdControlDealt":201,"totalUnitsHealed":1,"minionsKilled":201,"neutralMinionsKilled":16,"neutralMinionsKilledTeamJungle":15,"neutralMinionsKilledEnemyJungle":0,"goldEarned":15473,"goldSpent":14980,"combatPlayerScore":0,"objectivePlayerScore":0,"playerScore0":0,"playerScore1":0,"playerScore2":0,"playerScore3":0,"playerScore4":0,"playerScore5":0,"playerScore6":0,"playerScore7":0,"playerScore8":0,"playerScore9":0,"playerScore10":0,"playerScore11":0,"totalPlayerScore":0,"totalScoreRank":0,"nodeCapture":0,"nodeCaptureAssist":0,"nodeNeutralize":0,"nodeNeutralizeAssist":0,"teamObjective":0,"magicDamageDealtToChampions":0,"physicalDamageDealtToChampions":28606,"trueDamageDealtToChampions":646,"totalDamageDealtToChampions":29252,"visionWardsBoughtInGame":0,"sightWardsBoughtInGame":0,"wardsPlaced":5,"wardsKilled":1,"magicDamageDealt":0,"physicalDamageDealt":176675,"trueDamageDealt":646,"magicDamageTaken":14114,"physicalDamageTaken":34943,"trueDamageTaken":3857,"firstBloodKill":false,"firstBloodAssist":false,"firstTowerKill":true,"firstTowerAssist":false,"firstInhibitorKill":false,"firstInhibitorAssist":false,"wasAfk":false,"wasAfkAfterFailedSurrender":false,"inhibitorKills":1,"towerKills":1,"gameEndedInEarlySurrender":false,"gameEndedInSurrender":false,"causedEarlySurrender":false,"earlySurrenderAccomplice":false,"teamEarlySurrendered":false,"championTransform":0,"spell1Casts":263,"spell2Casts":27,"spell3Casts":82,"spell4Casts":16,"summoner1Casts":3,"summoner2Casts":5,"perk0":8010,"perk0Var1":511,"perk0Var2":0,"perk0Var3":0,"perk1":9111,"perk1Var1":1096,"perk1Var2":420,"perk1Var3":0,"perk2":9104,"perk2Var1":15,"perk2Var2":30,"perk2Var3":0,"perk3":8299,"perk3Var1":970,"perk3Var2":0,"perk3Var3":0,"perk4":8473,"perk4Var1":924,"perk4Var2":0,"perk4Var3":0,"perk5":8453,"perk5Var1":1522,"perk5Var2":83,"perk5Var3":0,"perkPrimaryStyle":8000,"perkSubStyle":8400,"championMissionStat0":0,"championMissionStat1":0,"championMissionStat2":0,"championMissionStat3":0,"totalHealsOnTeammates":0,"totalDamageShieldedOnTeammates":0,"teamPosition":"TOP","individualPosition":"TOP","statPerk0":5008,"statPerk1":5008,"statPerk2":5002},"timeAddedToQueue":1576517784291,"summonerId":2978868743,"wardSkin":111,"participantId":9,"partnerId":"","obfuscatedIP":"3VoTUXLOxMy1OmdTUitHpqfdYIc=","summonerLevel":155,"timeline":{"creepsPerMinDeltas":{"10-20":7.3,"0-10":6.4,"30-end":2,"20-30":5.4},"xpPerMinDeltas":{"10-20":620.5,"0-10":456.9,"30-end":762.2,"20-30":482.29999999999995},"goldPerMinDeltas":{"10-20":511,"0-10":291,"30-end":520,"20-30":332.70000000000005},"csDiffPerMinDeltas":{"10-20":1,"0-10":1.9,"30-end":-2.4000000000000004,"20-30":0.8999999999999999},"xpDiffPerMinDeltas":{"10-20":150,"0-10":33.19999999999999,"30-end":453.6,"20-30":-23.80000000000001},"damageTakenPerMinDeltas":{"10-20":1213.8,"0-10":525.1,"30-end":2057,"20-30":2272.1},"damageTakenDiffPerMinDeltas":{"10-20":463.99999999999994,"0-10":-23.099999999999994,"30-end":1070.4,"20-30":1211.6000000000001},"wardsPerMinDeltas":{"10-20":0.3,"0-10":0.2,"30-end":0,"20-30":0},"assistedLaneKillsPerMinDeltas":{"10-20":0,"0-10":0.1,"30-end":0,"20-30":0},"assistedLaneDeathsPerMinDeltas":{"10-20":0,"0-10":0,"30-end":0,"20-30":0.1},"towerKillsPerMinCounts":{"10-20":0.1,"0-10":0,"30-end":0,"20-30":0},"towerAssistsPerMinCounts":{"10-20":0,"0-10":0,"30-end":0,"20-30":0},"inhibitorKillsPerMinCounts":{"10-20":0,"0-10":0,"30-end":0,"20-30":0},"inhibitorAssistsPerMinCounts":{"10-20":0,"0-10":0,"30-end":0,"20-30":0},"baronKillsPerMinCounts":{"10-20":0,"0-10":0,"30-end":0,"20-30":0},"baronAssistsPerMinCounts":{"10-20":0,"0-10":0,"30-end":0,"20-30":0},"dragonKillsPerMinCounts":{"10-20":0,"0-10":0,"30-end":0,"20-30":0},"dragonAssistsPerMinCounts":{"10-20":0,"0-10":0,"30-end":0,"20-30":0},"vilemawKillsPerMinCounts":{"10-20":0,"0-10":0,"30-end":0,"20-30":0},"vilemawAssistsPerMinCounts":{"10-20":0,"0-10":0,"30-end":0,"20-30":0},"elderLizardKillsPerMinCounts":{"10-20":0,"0-10":0,"30-end":0,"20-30":0},"elderLizardAssistsPerMinCounts":{"10-20":0,"0-10":0,"30-end":0,"20-30":0},"ancientGolemKillsPerMinCounts":{"10-20":0,"0-10":0,"30-end":0,"20-30":0},"ancientGolemAssistsPerMinCounts":{"10-20":0,"0-10":0,"30-end":0,"20-30":0},"role":"SOLO","lane":"TOP"},"emoteIds":[3104,1487,1444,3148,1462,3220,1487,3251,3134]},{"originalAccountId":2941224307,"originalPlatformId":"HN1","currentAccountId":2941224307,"currentPlatformId":"HN1","teamId":200,"spell1Id":4,"spell2Id":12,"championId":13,"skinIndex":3,"profileIconId":983,"summonerName":"17\u5c81\u4e2d\u5355\u5fc3\u6001\u5d29\u4e86","teamParticipantId":5,"queueRating":1587,"stats":{"win":"Win","winner":true,"leaver":false,"timePlayed":2199,"totalTimeSpentDisconnected":0,"champLevel":18,"item0":3110,"item1":3800,"item2":3040,"item3":3111,"item4":3165,"item5":3116,"item6":3363,"kills":15,"doubleKills":2,"tripleKills":0,"quadraKills":0,"pentaKills":0,"unrealKills":0,"largestKillingSpree":6,"largestMultiKill":2,"killingSprees":4,"longestTimeSpentLiving":403,"deaths":12,"totalTimeSpentDead":427,"assists":12,"totalDamageDealt":229351,"totalDamageTaken":45197,"largestCriticalStrike":0,"totalHeal":12177,"damageSelfMitigated":34426,"damageDealtToObjectives":13554,"damageDealtToTurrets":5854,"visionScore":35,"timeCCingOthers":46,"totalTimeCrowdControlDealt":589,"totalUnitsHealed":1,"minionsKilled":191,"neutralMinionsKilled":24,"neutralMinionsKilledTeamJungle":17,"neutralMinionsKilledEnemyJungle":0,"goldEarned":18582,"goldSpent":17460,"combatPlayerScore":0,"objectivePlayerScore":0,"playerScore0":0,"playerScore1":0,"playerScore2":0,"playerScore3":0,"playerScore4":0,"playerScore5":0,"playerScore6":0,"playerScore7":0,"playerScore8":0,"playerScore9":0,"playerScore10":0,"playerScore11":0,"totalPlayerScore":0,"totalScoreRank":0,"nodeCapture":0,"nodeCaptureAssist":0,"nodeNeutralize":0,"nodeNeutralizeAssist":0,"teamObjective":0,"magicDamageDealtToChampions":36530,"physicalDamageDealtToChampions":1142,"trueDamageDealtToChampions":825,"totalDamageDealtToChampions":38498,"visionWardsBoughtInGame":2,"sightWardsBoughtInGame":0,"wardsPlaced":8,"wardsKilled":2,"magicDamageDealt":217684,"physicalDamageDealt":10557,"trueDamageDealt":1109,"magicDamageTaken":16697,"physicalDamageTaken":26979,"trueDamageTaken":1520,"firstBloodKill":false,"firstBloodAssist":false,"firstTowerKill":false,"firstTowerAssist":false,"firstInhibitorKill":false,"firstInhibitorAssist":false,"wasAfk":false,"wasAfkAfterFailedSurrender":false,"inhibitorKills":0,"towerKills":1,"gameEndedInEarlySurrender":false,"gameEndedInSurrender":false,"causedEarlySurrender":false,"earlySurrenderAccomplice":false,"teamEarlySurrendered":false,"championTransform":0,"spell1Casts":289,"spell2Casts":90,"spell3Casts":333,"spell4Casts":8,"summoner1Casts":4,"summoner2Casts":3,"perk0":8230,"perk0Var1":26,"perk0Var2":0,"perk0Var3":0,"perk1":8226,"perk1Var1":250,"perk1Var2":1870,"perk1Var3":0,"perk2":8210,"perk2Var1":40,"perk2Var2":0,"perk2Var3":0,"perk3":8236,"perk3Var1":48,"perk3Var2":0,"perk3Var3":0,"perk4":8139,"perk4Var1":1388,"perk4Var2":0,"perk4Var3":0,"perk5":8135,"perk5Var1":10111,"perk5Var2":5,"perk5Var3":0,"perkPrimaryStyle":8200,"perkSubStyle":8100,"championMissionStat0":0,"championMissionStat1":0,"championMissionStat2":0,"championMissionStat3":0,"totalHealsOnTeammates":0,"totalDamageShieldedOnTeammates":0,"teamPosition":"MIDDLE","individualPosition":"MIDDLE","statPerk0":5005,"statPerk1":5008,"statPerk2":5001},"timeAddedToQueue":1576517784291,"summonerId":2941224307,"wardSkin":97,"participantId":10,"partnerId":"","obfuscatedIP":"3VoTUXLOxMy1OmdTUitHpqfdYIc=","summonerLevel":52,"timeline":{"creepsPerMinDeltas":{"10-20":5.800000000000001,"0-10":6.5,"30-end":5.2,"20-30":3.8},"xpPerMinDeltas":{"10-20":475.1,"0-10":446.5,"30-end":833.2,"20-30":475.3},"goldPerMinDeltas":{"10-20":466.6,"0-10":317.79999999999995,"30-end":709.6,"20-30":554},"csDiffPerMinDeltas":{"10-20":-1.4999999999999996,"0-10":0.10000000000000009,"30-end":1.6,"20-30":2.2},"xpDiffPerMinDeltas":{"10-20":-108.39999999999998,"0-10":32.099999999999994,"30-end":74.80000000000007,"20-30":47.900000000000034},"damageTakenPerMinDeltas":{"10-20":1064.4,"0-10":395.6,"30-end":1703,"20-30":1747.1},"damageTakenDiffPerMinDeltas":{"10-20":588.7,"0-10":0.700000000000017,"30-end":-633,"20-30":864.5},"wardsPerMinDeltas":{"10-20":0.4,"0-10":0.30000000000000004,"30-end":0,"20-30":0.1},"assistedLaneKillsPerMinDeltas":{"10-20":0,"0-10":0,"30-end":0.2,"20-30":0},"assistedLaneDeathsPerMinDeltas":{"10-20":0.2,"0-10":0,"30-end":0,"20-30":0},"towerKillsPerMinCounts":{"10-20":0,"0-10":0,"30-end":0,"20-30":0},"towerAssistsPerMinCounts":{"10-20":0,"0-10":0,"30-end":0,"20-30":0},"inhibitorKillsPerMinCounts":{"10-20":0,"0-10":0,"30-end":0,"20-30":0},"inhibitorAssistsPerMinCounts":{"10-20":0,"0-10":0,"30-end":0,"20-30":0},"baronKillsPerMinCounts":{"10-20":0,"0-10":0,"30-end":0,"20-30":0},"baronAssistsPerMinCounts":{"10-20":0,"0-10":0,"30-end":0,"20-30":0},"dragonKillsPerMinCounts":{"10-20":0,"0-10":0,"30-end":0,"20-30":0},"dragonAssistsPerMinCounts":{"10-20":0,"0-10":0,"30-end":0,"20-30":0},"vilemawKillsPerMinCounts":{"10-20":0,"0-10":0,"30-end":0,"20-30":0},"vilemawAssistsPerMinCounts":{"10-20":0,"0-10":0,"30-end":0,"20-30":0},"elderLizardKillsPerMinCounts":{"10-20":0,"0-10":0,"30-end":0,"20-30":0},"elderLizardAssistsPerMinCounts":{"10-20":0,"0-10":0,"30-end":0,"20-30":0},"ancientGolemKillsPerMinCounts":{"10-20":0.1,"0-10":0,"30-end":0,"20-30":0},"ancientGolemAssistsPerMinCounts":{"10-20":0,"0-10":0,"30-end":0,"20-30":0},"role":"SOLO","lane":"MID"},"emoteIds":[1444,1505,1445,1505,1459,1505,1505,1505,1505]}]}}